Whispr/__init__.py
whispr_s1nfex-0.1.dist-info/METADATA
whispr_s1nfex-0.1.dist-info/WHEEL
whispr_s1nfex-0.1.dist-info/top_level.txt
whispr_s1nfex-0.1.dist-info/RECORD
