Metadata-Version: 2.4
Name: Whispr-s1nfex
Version: 0.1
Summary: S1nfex package
Home-page: https://example.com
Author: S1nfex
Author-email: rirbd70@gmail.com
Classifier: Programming Language :: Python :: 3
Requires-Python: >=3.6
Dynamic: author
Dynamic: author-email
Dynamic: classifier
Dynamic: description
Dynamic: description-content-type
Dynamic: home-page
Dynamic: requires-python
Dynamic: summary
